{
  "bill": {
    "from_organization": "~{\"classification\": \"lower\"}",
    "identifier": "HF 3769",
    "legislative_session": "2025-2026",
    "subject": [
      "Corrections and Corrections Department",
      "Health and Health Department",
      "Mental Health and Related Conditions"
    ],
    "title": "Multiple levels of substance abuse care provided by the commissioner of corrections clarified in law, access to mental health unit beds for incarcerated persons expanded, and mandatory tuberculosis screening in correctional facilities clarified."
  },
  "id": "HF 3769",
  "log": {
    "action": {
      "classification": [
        "committee-passage"
      ],
      "date": "2026-03-09",
      "description": "Committee report, to adopt and re-refer to Health Finance and Policy",
      "organization_id": "~{\"classification\": \"lower\"}"
    },
    "bill_id": "HF 3769"
  },
  "sources": {
    "bill": "mn-legislation/country:us/state:mn/sessions/2025-2026/bills/HF3769/metadata.json",
    "log": "mn-legislation/country:us/state:mn/sessions/2025-2026/bills/HF3769/logs/20260309T000000Z_committee_report_to_adopt_and_rerefer_to_health_finance_and_policy.json"
  },
  "timestamp": "20260309T000000Z"
}
