{
  "bill": {
    "abstracts": [
      {
        "abstract": "This measure would designate April 28, 2026, as School Bus Drivers' Day in California, in order to draw special public attention to school bus drivers for their continued and excellent services to pupils in California.",
        "note": "summary"
      }
    ],
    "from_organization": "~{\"classification\": \"upper\"}",
    "identifier": "SCR157",
    "legislative_session": "20252026",
    "subject": [
      "SchoolBusDrivers'Day"
    ],
    "title": "Relative to School Bus Drivers' Day."
  },
  "id": "SCR157",
  "log": {
    "action": {
      "classification": [
        "became-law"
      ],
      "date": "2026-05-21",
      "description": "Chaptered by Secretary of State. Res. Chapter 72, Statutes of 2026.",
      "organization_id": "~{\"classification\": \"legislature\"}"
    },
    "bill_id": "SCR157"
  },
  "sources": {
    "bill": "ca-legislation/country:us/state:ca/sessions/20252026/bills/SCR157/metadata.json",
    "log": "ca-legislation/country:us/state:ca/sessions/20252026/bills/SCR157/logs/20260521T000000Z.classification.became-law.legislature.json"
  }
}
