{
  "bill": {
    "from_organization": "~{\"classification\": \"lower\"}",
    "identifier": "HB33",
    "legislative_session": "2026",
    "subject": [
      "Accountability, Efficiency, Transparency",
      "Apportionment and Elections"
    ],
    "title": "Online voter registration; authorize for first-time registrants."
  },
  "id": "HB33",
  "log": {
    "action": {
      "date": "2026-02-03T06:00:00+00:00",
      "description": "Died In Committee",
      "organization_id": "~{\"classification\": \"lower\"}"
    },
    "bill_id": "HB33"
  },
  "sources": {
    "bill": "ms-legislation/country:us/state:ms/sessions/2026/bills/HB33/metadata.json",
    "log": "ms-legislation/country:us/state:ms/sessions/2026/bills/HB33/logs/20260203T060000Z_died_in_committee.json"
  },
  "timestamp": "20260203T060000Z"
}
